irori/__init__.py
irori/depend.py
irori/runner.py
irori/context/__init__.py
irori/context/base.py
irori/context/build.py
irori/context/runtime.py
irori/executors/__init__.py
irori/rules/__init__.py
irori/rules/base.py
irori/rules/depend.py
irori/rules/link.py
irori/rules/static.py
irori/rules/suffix.py
irori-1.0.0.dist-info/LICENSE
irori-1.0.0.dist-info/METADATA
irori-1.0.0.dist-info/WHEEL
irori-1.0.0.dist-info/top_level.txt
irori-1.0.0.dist-info/RECORD
